airflow_bootstrap_utils/__init__.py
airflow_bootstrap_utils/console_helper.py
airflow_bootstrap_utils/constants.py
airflow_bootstrap_utils/file_utils.py
airflow_bootstrap_utils/generate_dag.py
airflow_bootstrap_utils/manager.py
airflow_bootstrap_utils/system_caller.py
airflow_bootstrap_utils/conf/config.yaml
airflow_bootstrap_utils/template/manager.py
airflow_bootstrap_utils/templates/dag_template.py
airflow_bootstrap_utils/templates/task_template.py
airflow_bootstrap_utils-0.2.0.dist-info/AUTHORS.rst
airflow_bootstrap_utils-0.2.0.dist-info/METADATA
airflow_bootstrap_utils-0.2.0.dist-info/WHEEL
airflow_bootstrap_utils-0.2.0.dist-info/entry_points.txt
airflow_bootstrap_utils-0.2.0.dist-info/top_level.txt
airflow_bootstrap_utils-0.2.0.dist-info/RECORD
