Metadata-Version: 2.1
Name: airflow_bootstrap_utils
Version: 0.2.0
Summary: Collection of Python tools to generate Airflow DAGs from control and configuration files.
Home-page: https://github.com/jai-python3/airflow_bootstrap_utils
Author: Jaideep Sundaram
Author-email: jai.python3@gmail.com
Keywords: airflow_bootstrap_utils
Classifier: Development Status :: 2 - Pre-Alpha
Classifier: Intended Audience :: Developers
Classifier: Natural Language :: English
Classifier: Programming Language :: Python :: 3
Classifier: Programming Language :: Python :: 3.6
Classifier: Programming Language :: Python :: 3.7
Classifier: Programming Language :: Python :: 3.8
Requires-Python: >=3.6
License-File: AUTHORS.rst
Requires-Dist: Click >=7.0
Requires-Dist: jinja2
Requires-Dist: Rich
Requires-Dist: PyYAML
Requires-Dist: simple-template-toolkit
